game_client.py
game_api_client-0.0.2.dist-info/METADATA
game_api_client-0.0.2.dist-info/WHEEL
game_api_client-0.0.2.dist-info/licenses/LICENSE
game_api_client-0.0.2.dist-info/RECORD
