Metadata-Version: 2.4
Name: game-api-client
Version: 0.0.2
Summary: Python client library for GAME trading API
License: MIT
License-File: LICENSE
Keywords: api,trading,game,client
Author: Groupe E
Author-email: support@groupe-e.ch
Requires-Python: >=3.8,<4.0
Classifier: Development Status :: 5 - Production/Stable
Classifier: Intended Audience :: Developers
Classifier: License :: OSI Approved :: MIT License
Classifier: Programming Language :: Python :: 3
Classifier: Programming Language :: Python :: 3.8
Classifier: Programming Language :: Python :: 3.9
Classifier: Programming Language :: Python :: 3.10
Classifier: Programming Language :: Python :: 3.11
Classifier: Programming Language :: Python :: 3.12
Classifier: Programming Language :: Python :: 3.13
Classifier: Programming Language :: Python :: 3.14
Classifier: Topic :: Software Development :: Libraries :: Python Modules
Requires-Dist: httpx (>=0.28.1,<0.29.0)
Requires-Dist: pydantic (>=2.10.0,<3.0.0)
Project-URL: Documentation, https://github.com/groupe-e/game-api-client#readme
Project-URL: Homepage, https://github.com/groupe-e/game-api-client
Project-URL: Repository, https://github.com/groupe-e/game-api-client
